snakefetch.py
snakefetch-0.5.1.dist-info/LICENSE
snakefetch-0.5.1.dist-info/METADATA
snakefetch-0.5.1.dist-info/WHEEL
snakefetch-0.5.1.dist-info/entry_points.txt
snakefetch-0.5.1.dist-info/top_level.txt
snakefetch-0.5.1.dist-info/RECORD
