Metadata-Version: 2.1
Name: snakefetch
Version: 0.5.1
Summary: Fetches workflow and config files from a Snakemake repository on GitHub
Home-page: https://github.com/niekwit/snakefetch/tree/main
Author: Niek Wit
Author-email: nw416@cam.ac.uk
Project-URL: Source, https://github.com/niekwit/snakefetch/tree/main
Classifier: Programming Language :: Python :: 3
Classifier: License :: OSI Approved :: MIT License
Classifier: Operating System :: POSIX :: Linux
Requires-Python: >=3.10
License-File: LICENSE
